scw/__init__.py
scw/config.py
scw/config_file_watcher.py
scw/log.py
scw/options.py
scw/watcher_app.py
scw/cli/__init__.py
scw/cli/screen_config_watcher.py
scw/screen_lock/__init__.py
scw/screen_lock/macos.py
screen_config_watcher-0.0.4.dist-info/LICENSE
screen_config_watcher-0.0.4.dist-info/METADATA
screen_config_watcher-0.0.4.dist-info/WHEEL
screen_config_watcher-0.0.4.dist-info/entry_points.txt
screen_config_watcher-0.0.4.dist-info/top_level.txt
screen_config_watcher-0.0.4.dist-info/RECORD
